[
  {
    "id": 4157397571,
    "node_id": "PRR_kwDOEHbxG873zNpD",
    "user": {
      "login": "jellejurre",
      "id": 76777936,
      "node_id": "MDQ6VXNlcjc2Nzc3OTM2",
      "avatar_url": "https://avatars.githubusercontent.com/u/76777936?u=8b1fc3907f0f8cc168834f5940e42bfb086ac3c6&v=4",
      "gravatar_id": "",
      "url": "https://api.github.com/users/jellejurre",
      "html_url": "https://github.com/jellejurre",
      "followers_url": "https://api.github.com/users/jellejurre/followers",
      "following_url": "https://api.github.com/users/jellejurre/following{/other_user}",
      "gists_url": "https://api.github.com/users/jellejurre/gists{/gist_id}",
      "starred_url": "https://api.github.com/users/jellejurre/starred{/owner}{/repo}",
      "subscriptions_url": "https://api.github.com/users/jellejurre/subscriptions",
      "organizations_url": "https://api.github.com/users/jellejurre/orgs",
      "repos_url": "https://api.github.com/users/jellejurre/repos",
      "events_url": "https://api.github.com/users/jellejurre/events{/privacy}",
      "received_events_url": "https://api.github.com/users/jellejurre/received_events",
      "type": "User",
      "user_view_type": "public",
      "site_admin": false
    },
    "body": "",
    "state": "COMMENTED",
    "html_url": "https://github.com/doldecomp/melee/pull/2430#pullrequestreview-4157397571",
    "pull_request_url": "https://api.github.com/repos/doldecomp/melee/pulls/2430",
    "author_association": "COLLABORATOR",
    "_links": {
      "html": {
        "href": "https://github.com/doldecomp/melee/pull/2430#pullrequestreview-4157397571"
      },
      "pull_request": {
        "href": "https://api.github.com/repos/doldecomp/melee/pulls/2430"
      }
    },
    "submitted_at": "2026-04-22T19:27:32Z",
    "commit_id": "e577194cac87f1b903bf743ac20177b3d2a17179"
  },
  {
    "id": 4157428820,
    "node_id": "PRR_kwDOEHbxG873zVRU",
    "user": {
      "login": "lukechampine",
      "id": 3344749,
      "node_id": "MDQ6VXNlcjMzNDQ3NDk=",
      "avatar_url": "https://avatars.githubusercontent.com/u/3344749?u=868b0a0001c24270c0cd5a63ba997f5c751c6587&v=4",
      "gravatar_id": "",
      "url": "https://api.github.com/users/lukechampine",
      "html_url": "https://github.com/lukechampine",
      "followers_url": "https://api.github.com/users/lukechampine/followers",
      "following_url": "https://api.github.com/users/lukechampine/following{/other_user}",
      "gists_url": "https://api.github.com/users/lukechampine/gists{/gist_id}",
      "starred_url": "https://api.github.com/users/lukechampine/starred{/owner}{/repo}",
      "subscriptions_url": "https://api.github.com/users/lukechampine/subscriptions",
      "organizations_url": "https://api.github.com/users/lukechampine/orgs",
      "repos_url": "https://api.github.com/users/lukechampine/repos",
      "events_url": "https://api.github.com/users/lukechampine/events{/privacy}",
      "received_events_url": "https://api.github.com/users/lukechampine/received_events",
      "type": "User",
      "user_view_type": "public",
      "site_admin": false
    },
    "body": "",
    "state": "COMMENTED",
    "html_url": "https://github.com/doldecomp/melee/pull/2430#pullrequestreview-4157428820",
    "pull_request_url": "https://api.github.com/repos/doldecomp/melee/pulls/2430",
    "author_association": "CONTRIBUTOR",
    "_links": {
      "html": {
        "href": "https://github.com/doldecomp/melee/pull/2430#pullrequestreview-4157428820"
      },
      "pull_request": {
        "href": "https://api.github.com/repos/doldecomp/melee/pulls/2430"
      }
    },
    "submitted_at": "2026-04-22T19:33:54Z",
    "commit_id": "e577194cac87f1b903bf743ac20177b3d2a17179"
  },
  {
    "id": 4157540882,
    "node_id": "PRR_kwDOEHbxG873zwoS",
    "user": {
      "login": "jellejurre",
      "id": 76777936,
      "node_id": "MDQ6VXNlcjc2Nzc3OTM2",
      "avatar_url": "https://avatars.githubusercontent.com/u/76777936?u=8b1fc3907f0f8cc168834f5940e42bfb086ac3c6&v=4",
      "gravatar_id": "",
      "url": "https://api.github.com/users/jellejurre",
      "html_url": "https://github.com/jellejurre",
      "followers_url": "https://api.github.com/users/jellejurre/followers",
      "following_url": "https://api.github.com/users/jellejurre/following{/other_user}",
      "gists_url": "https://api.github.com/users/jellejurre/gists{/gist_id}",
      "starred_url": "https://api.github.com/users/jellejurre/starred{/owner}{/repo}",
      "subscriptions_url": "https://api.github.com/users/jellejurre/subscriptions",
      "organizations_url": "https://api.github.com/users/jellejurre/orgs",
      "repos_url": "https://api.github.com/users/jellejurre/repos",
      "events_url": "https://api.github.com/users/jellejurre/events{/privacy}",
      "received_events_url": "https://api.github.com/users/jellejurre/received_events",
      "type": "User",
      "user_view_type": "public",
      "site_admin": false
    },
    "body": "",
    "state": "APPROVED",
    "html_url": "https://github.com/doldecomp/melee/pull/2430#pullrequestreview-4157540882",
    "pull_request_url": "https://api.github.com/repos/doldecomp/melee/pulls/2430",
    "author_association": "COLLABORATOR",
    "_links": {
      "html": {
        "href": "https://github.com/doldecomp/melee/pull/2430#pullrequestreview-4157540882"
      },
      "pull_request": {
        "href": "https://api.github.com/repos/doldecomp/melee/pulls/2430"
      }
    },
    "submitted_at": "2026-04-22T19:55:40Z",
    "commit_id": "df27c2cf7f8cc46494cc012e8a862f3ee3f9dea7"
  },
  {
    "id": 4159811312,
    "node_id": "PRR_kwDOEHbxG8738a7w",
    "user": {
      "login": "Ari4ka",
      "id": 166764074,
      "node_id": "U_kgDOCfCeKg",
      "avatar_url": "https://avatars.githubusercontent.com/u/166764074?v=4",
      "gravatar_id": "",
      "url": "https://api.github.com/users/Ari4ka",
      "html_url": "https://github.com/Ari4ka",
      "followers_url": "https://api.github.com/users/Ari4ka/followers",
      "following_url": "https://api.github.com/users/Ari4ka/following{/other_user}",
      "gists_url": "https://api.github.com/users/Ari4ka/gists{/gist_id}",
      "starred_url": "https://api.github.com/users/Ari4ka/starred{/owner}{/repo}",
      "subscriptions_url": "https://api.github.com/users/Ari4ka/subscriptions",
      "organizations_url": "https://api.github.com/users/Ari4ka/orgs",
      "repos_url": "https://api.github.com/users/Ari4ka/repos",
      "events_url": "https://api.github.com/users/Ari4ka/events{/privacy}",
      "received_events_url": "https://api.github.com/users/Ari4ka/received_events",
      "type": "User",
      "user_view_type": "public",
      "site_admin": false
    },
    "body": "",
    "state": "APPROVED",
    "html_url": "https://github.com/doldecomp/melee/pull/2430#pullrequestreview-4159811312",
    "pull_request_url": "https://api.github.com/repos/doldecomp/melee/pulls/2430",
    "author_association": "NONE",
    "_links": {
      "html": {
        "href": "https://github.com/doldecomp/melee/pull/2430#pullrequestreview-4159811312"
      },
      "pull_request": {
        "href": "https://api.github.com/repos/doldecomp/melee/pulls/2430"
      }
    },
    "submitted_at": "2026-04-23T05:15:29Z",
    "commit_id": "df27c2cf7f8cc46494cc012e8a862f3ee3f9dea7"
  }
]
