{
  "id": "resource_guides",
  "kind": "document",
  "title": "Resource guides and manifests",
  "trust_tier": "historical",
  "freshness": "snapshot",
  "description": "Cross-source resource guide, acquisition manifests, and resource notes co-located under the source system.",
  "data_paths": [
    "knowledge/sources/resource_guides/data"
  ],
  "index_outputs": [
    "knowledge/sources/resource_guides/indexes/chunks.jsonl"
  ],
  "commands": {
    "status": "python3 knowledge/sources/resource_guides/api/status.py --json",
    "search": "python3 knowledge/sources/resource_guides/api/search.py --query <query> --json"
  },
  "capabilities": [
    "search",
    "resource_manifest"
  ]
}
